chart_mcp/__init__.py
chart_mcp-0.1.1.dist-info/WHEEL
chart_mcp-0.1.1.dist-info/entry_points.txt
chart_mcp-0.1.1.dist-info/METADATA
chart_mcp-0.1.1.dist-info/RECORD
