Metadata-Version: 2.3
Name: chart-mcp
Version: 0.1.1
Summary: MCP server for generating performance comparison charts
Requires-Dist: mcp[cli]>=1.25.0
Requires-Dist: matplotlib>=3.7.0
Requires-Dist: numpy>=1.24.0
Requires-Python: >=3.11
